cmc_api/__init__.py
cmc_api/cmc.py
cmc_api/cmc_datahandler.py
cmc_api/cmc_helper.py
cmc_api/cmc_utils.py
cmc_api_wrapper-0.1.18.dist-info/LICENSE
cmc_api_wrapper-0.1.18.dist-info/METADATA
cmc_api_wrapper-0.1.18.dist-info/WHEEL
cmc_api_wrapper-0.1.18.dist-info/top_level.txt
cmc_api_wrapper-0.1.18.dist-info/RECORD
