Metadata-Version: 2.1
Name: cmc-api-wrapper
Version: 0.1.18
Summary: A wrapper for the Con Market Cap API
Home-page: https://github.com/CubeVic/coinmarketcapAPI
Author: Victor Andres Aguirre Fernandez
Author-email: victoraguirre.f@gmail.com
Project-URL: Bug Tracker, https://github.com/CubeVic/coinmarketcapAPI/issues
Keywords: ['python-client','CoinMarketCap','crypto']
Classifier: Programming Language :: Python :: 3
Classifier: License :: OSI Approved :: MIT License
Classifier: Operating System :: OS Independent
Requires-Python: >=3.10
License-File: LICENSE
Requires-Dist: requests
